lume_model/__init__.py
lume_model/_version.py
lume_model/base.py
lume_model/mlflow_utils.py
lume_model/utils.py
lume_model/variables.py
lume_model/models/__init__.py
lume_model/models/ensemble.py
lume_model/models/gp_model.py
lume_model/models/prob_model_base.py
lume_model/models/torch_model.py
lume_model/models/torch_module.py
lume_model/models/utils.py
lume_model-2.0.1.dist-info/licenses/LICENSE
lume_model-2.0.1.dist-info/METADATA
lume_model-2.0.1.dist-info/WHEEL
lume_model-2.0.1.dist-info/top_level.txt
lume_model-2.0.1.dist-info/RECORD
