Metadata-Version: 2.4
Name: lume-model
Version: 2.0.1
Summary: Data structures used in the LUME modeling toolset.
Author: SLAC National Accelerator Laboratory
License: Copyright (c) 2017-2020, The Board of Trustees of the Leland Stanford
Project-URL: Homepage, https://github.com/slaclab/lume-model
Project-URL: Documentation, https://slaclab.github.io/lume-model/
Project-URL: Bug Tracker, https://github.com/slaclab/lume-model/issues
Keywords: machine learning,accelerator physics
Classifier: Natural Language :: English
Classifier: Programming Language :: Python :: 3 :: Only
Classifier: Programming Language :: Python :: 3.10
Classifier: Programming Language :: Python :: 3.11
Classifier: Programming Language :: Python :: 3.12
Classifier: Intended Audience :: Science/Research
Classifier: Topic :: Scientific/Engineering
Requires-Python: >=3.10
License-File: LICENSE
Requires-Dist: pydantic
Requires-Dist: numpy
Requires-Dist: pyyaml
Requires-Dist: torch
Requires-Dist: botorch>=0.15
Requires-Dist: mlflow
Provides-Extra: dev
Requires-Dist: pre-commit; extra == "dev"
Requires-Dist: pytest; extra == "dev"
Provides-Extra: docs
Requires-Dist: mkdocs; extra == "docs"
Requires-Dist: mkdocstrings; extra == "docs"
Requires-Dist: mkdocstrings-python; extra == "docs"
Requires-Dist: mkdocs-material; extra == "docs"
Requires-Dist: mkdocs-include-markdown-plugin; extra == "docs"
Dynamic: license-file
